edulint/__init__.py
edulint/__main__.py
edulint/edulint.py
edulint/explanations.py
edulint/explanations.toml
edulint/linters.py
edulint/option_parses.py
edulint/options.py
edulint/version.py
edulint/config/__init__.py
edulint/config/arg.py
edulint/config/config.py
edulint/config/file_config.py
edulint/config/language_translations.py
edulint/config/option_sets.py
edulint/config/raw_flake8_patterns.py
edulint/config/utils.py
edulint/config/files/cs0.toml
edulint/config/files/cs1.toml
edulint/config/files/default.toml
edulint/config/files/empty.toml
edulint/config/files/full.toml
edulint/config/files/webtiger.toml
edulint/linting/__init__.py
edulint/linting/linting.py
edulint/linting/nonparsing_checkers.py
edulint/linting/overrides.py
edulint/linting/problem.py
edulint/linting/process_handler.py
edulint/linting/tweakers.py
edulint/linting/analyses/__init__.py
edulint/linting/analyses/_z3.py
edulint/linting/analyses/antiunify.py
edulint/linting/analyses/data_dependency.py
edulint/linting/analyses/mutability.py
edulint/linting/analyses/patcher.py
edulint/linting/analyses/types.py
edulint/linting/analyses/utils.py
edulint/linting/analyses/var_events.py
edulint/linting/analyses/variable_scope.py
edulint/linting/analyses/z3_analysis.py
edulint/linting/analyses/z3_block_analysis.py
edulint/linting/analyses/cfg/__init__.py
edulint/linting/analyses/cfg/dot_generator.py
edulint/linting/analyses/cfg/graph.py
edulint/linting/analyses/cfg/utils.py
edulint/linting/analyses/cfg/visitor.py
edulint/linting/checkers/__init__.py
edulint/linting/checkers/basic_checker.py
edulint/linting/checkers/local_defects.py
edulint/linting/checkers/old_duplication_checker.py
edulint/linting/checkers/python_ta_checkers.py
edulint/linting/checkers/simplifiable_if.py
edulint/linting/checkers/unsuited_loop.py
edulint/linting/checkers/duplication/__init__.py
edulint/linting/checkers/duplication/checker.py
edulint/linting/checkers/duplication/duplicate_block.py
edulint-4.3.1.dist-info/licenses/LICENSE
edulint-4.3.1.dist-info/METADATA
edulint-4.3.1.dist-info/WHEEL
edulint-4.3.1.dist-info/entry_points.txt
edulint-4.3.1.dist-info/top_level.txt
edulint-4.3.1.dist-info/RECORD
