Metadata-Version: 2.4
Name: edulint
Version: 4.3.1
Summary: Python linter aimed at helping novice programmers improve their coding style.
Home-page: https://github.com/GiraffeReversed/edulint
Author: Anna Rechtackova
Author-email: anna.rechtackova@mail.muni.cz
License: GPLv3
Classifier: Programming Language :: Python :: 3
Classifier: Programming Language :: Python :: 3.8
Classifier: Programming Language :: Python :: 3.9
Classifier: Programming Language :: Python :: 3.10
Classifier: Programming Language :: Python :: 3.11
Classifier: Programming Language :: Python :: 3.12
Classifier: Programming Language :: Python :: 3.13
Classifier: Programming Language :: Python :: 3.14
Classifier: License :: OSI Approved :: GNU General Public License v3 (GPLv3)
Classifier: Operating System :: OS Independent
Requires-Python: >=3.8
License-File: LICENSE
Requires-Dist: flake8<7.2,>=3.8.4
Requires-Dist: flake8-json~=24.4.0
Requires-Dist: pylint<3.3,>=3
Requires-Dist: dataclasses-json~=0.6.7
Requires-Dist: tomli~=2.0
Requires-Dist: requests~=2.31
Requires-Dist: platformdirs~=4.0
Requires-Dist: loguru
Dynamic: license-file
